Metadata-Version: 2.4
Name: iflow-mcp_mcp-server-calculator
Version: 0.2.0
Summary: A Model Context Protocol server for calculating
Project-URL: Source, https://github.com/githejie/mcp-server-calculator
Author-email: He Jie <hejie6173@gmail.com>
License: MIT
License-File: LICENSE
Keywords: calculator,llm,math,mcp
Classifier: Development Status :: 4 - Beta
Classifier: Intended Audience :: Developers
Classifier: License :: OSI Approved :: MIT License
Classifier: Programming Language :: Python :: 3
Classifier: Programming Language :: Python :: 3.10
Requires-Python: >=3.10
Requires-Dist: mcp>=1.4.1
